{"users": [{"fullname": "Bryce Adelstein Lelbach aka wash", "public_repo_count": 63, "score": 1.0, "repos": 63, "username": "brycelelbach", "followers": 149, "gravatar_id": "", "created": "2010-09-13T23:41:32Z", "name": "Bryce Adelstein Lelbach aka wash", "login": "brycelelbach", "id": "user-398194", "type": "user", "created_at": "2010-09-13T23:41:32Z", "language": "C++", "followers_count": 149, "location": "Santa Clara, CA"}, {"fullname": "Cody Seibert", "public_repo_count": 67, "score": 1.0, "repos": 67, "username": "codyseibert", "followers": 149, "gravatar_id": "", "created": "2012-06-19T17:43:50Z", "name": "Cody Seibert", "login": "codyseibert", "id": "user-1868782", "type": "user", "created_at": "2012-06-19T17:43:50Z", "language": "JavaScript", "followers_count": 149, "location": null}, {"fullname": "Jackie Luo", "public_repo_count": 38, "score": 1.0, "repos": 38, "username": "jackiehluo", "followers": 149, "gravatar_id": "", "created": "2014-08-14T21:23:32Z", "name": "Jackie Luo", "login": "jackiehluo", "id": "user-8452682", "type": "user", "created_at": "2014-08-14T21:23:32Z", "language": "CSS", "followers_count": 149, "location": "San Francisco"}, {"fullname": "Joss Mackison", "public_repo_count": 25, "score": 1.0, "repos": 25, "username": "jossmac", "followers": 149, "gravatar_id": "", "created": "2012-11-06T00:11:51Z", "name": "Joss Mackison", "login": "jossmac", "id": "user-2730833", "type": "user", "created_at": "2012-11-06T00:11:51Z", "language": "JavaScript", "followers_count": 149, "location": "Sydney, Australia"}, {"fullname": "Zac Gordon", "public_repo_count": 30, "score": 1.0, "repos": 30, "username": "zgordon", "followers": 149, "gravatar_id": "", "created": "2009-03-07T05:50:56Z", "name": "Zac Gordon", "login": "zgordon", "id": "user-60997", "type": "user", "created_at": "2009-03-07T05:50:56Z", "language": "CSS", "followers_count": 149, "location": "DC, USA"}, {"fullname": "Anton Burnashev", "public_repo_count": 28, "score": 1.0, "repos": 28, "username": "burnash", "followers": 149, "gravatar_id": "", "created": "2010-05-04T16:00:14Z", "name": "Anton Burnashev", "login": "burnash", "id": "user-264674", "type": "user", "created_at": "2010-05-04T16:00:14Z", "language": "Python", "followers_count": 149, "location": "Berlin"}, {"fullname": "Justin Gitlin", "public_repo_count": 26, "score": 1.0, "repos": 26, "username": "cacheflowe", "followers": 149, "gravatar_id": "", "created": "2010-07-31T08:21:21Z", "name": "Justin Gitlin", "login": "cacheflowe", "id": "user-349969", "type": "user", "created_at": "2010-07-31T08:21:21Z", "language": "JavaScript", "followers_count": 149, "location": "Denver, CO, USA"}, {"fullname": "Boris Lovosevic", "public_repo_count": 94, "score": 1.0, "repos": 94, "username": "loboris", "followers": 149, "gravatar_id": "", "created": "2013-12-29T10:34:55Z", "name": "Boris Lovosevic", "login": "loboris", "id": "user-6280349", "type": "user", "created_at": "2013-12-29T10:34:55Z", "language": "C", "followers_count": 149, "location": "Zagreb, Croatia"}, {"fullname": "Mario Casciaro", "public_repo_count": 31, "score": 1.0, "repos": 31, "username": "mariocasciaro", "followers": 149, "gravatar_id": "", "created": "2009-07-15T18:08:31Z", "name": "Mario Casciaro", "login": "mariocasciaro", "id": "user-105319", "type": "user", "created_at": "2009-07-15T18:08:31Z", "language": "JavaScript", "followers_count": 149, "location": "Dublin, Ireland"}, {"fullname": "Tugdual Grall", "public_repo_count": 92, "score": 1.0, "repos": 92, "username": "tgrall", "followers": 149, "gravatar_id": "", "created": "2010-12-30T05:57:57Z", "name": "Tugdual Grall", "login": "tgrall", "id": "user-541250", "type": "user", "created_at": "2010-12-30T05:57:57Z", "language": "Java", "followers_count": 149, "location": "Nantes, France"}, {"fullname": "\u7f57\u6cfd\u8f69", "public_repo_count": 80, "score": 1.0, "repos": 80, "username": "spacewander", "followers": 149, "gravatar_id": "", "created": "2013-04-15T14:28:50Z", "name": "\u7f57\u6cfd\u8f69", "login": "spacewander", "id": "user-4161644", "type": "user", "created_at": "2013-04-15T14:28:50Z", "language": "Python", "followers_count": 149, "location": "Zhuhai,China"}, {"fullname": "fanbingxin", "public_repo_count": 38, "score": 1.0, "repos": 38, "username": "icexin", "followers": 149, "gravatar_id": "", "created": "2012-11-03T05:49:55Z", "name": "fanbingxin", "login": "icexin", "id": "user-2713364", "type": "user", "created_at": "2012-11-03T05:49:55Z", "language": "Go", "followers_count": 149, "location": "beijing"}, {"fullname": "Lars Werkman", "public_repo_count": 10, "score": 1.0, "repos": 10, "username": "LarsWerkman", "followers": 149, "gravatar_id": "", "created": "2012-10-10T11:29:22Z", "name": "Lars Werkman", "login": "LarsWerkman", "id": "user-2527778", "type": "user", "created_at": "2012-10-10T11:29:22Z", "language": "Java", "followers_count": 149, "location": "Netherlands"}, {"fullname": "Romain Pouclet", "public_repo_count": 153, "score": 1.0, "repos": 153, "username": "Palleas", "followers": 149, "gravatar_id": "", "created": "2009-01-23T16:42:35Z", "name": "Romain Pouclet", "login": "Palleas", "id": "user-48797", "type": "user", "created_at": "2009-01-23T16:42:35Z", "language": "Swift", "followers_count": 149, "location": "Montreal, Quebec, Canada"}, {"fullname": "", "public_repo_count": 34, "score": 1.0, "repos": 34, "username": "magicae", "followers": 149, "gravatar_id": "", "created": "2014-02-22T00:59:20Z", "name": "", "login": "magicae", "id": "user-6753092", "type": "user", "created_at": "2014-02-22T00:59:20Z", "language": "JavaScript", "followers_count": 149, "location": null}, {"fullname": "Drew Crawford", "public_repo_count": 106, "score": 1.0, "repos": 106, "username": "drewcrawford", "followers": 149, "gravatar_id": "", "created": "2010-01-16T05:27:02Z", "name": "Drew Crawford", "login": "drewcrawford", "id": "user-183400", "type": "user", "created_at": "2010-01-16T05:27:02Z", "language": "Objective-C", "followers_count": 149, "location": "Austin, TX"}, {"fullname": "Ivan Medina Diaz", "public_repo_count": 231, "score": 1.0, "repos": 231, "username": "ivandevp", "followers": 149, "gravatar_id": "", "created": "2014-10-17T15:08:45Z", "name": "Ivan Medina Diaz", "login": "ivandevp", "id": "user-9284690", "type": "user", "created_at": "2014-10-17T15:08:45Z", "language": "JavaScript", "followers_count": 149, "location": "Lima, Per\u00fa"}, {"fullname": "hacfi", "public_repo_count": 79, "score": 1.0, "repos": 79, "username": "hacfi", "followers": 149, "gravatar_id": "", "created": "2010-10-05T23:33:28Z", "name": "hacfi", "login": "hacfi", "id": "user-428841", "type": "user", "created_at": "2010-10-05T23:33:28Z", "language": "PHP", "followers_count": 149, "location": "Berlin"}, {"fullname": "Sebastian Grewe", "public_repo_count": 16, "score": 1.0, "repos": 16, "username": "TheSerapher", "followers": 149, "gravatar_id": "", "created": "2012-09-19T08:33:03Z", "name": "Sebastian Grewe", "login": "TheSerapher", "id": "user-2376835", "type": "user", "created_at": "2012-09-19T08:33:03Z", "language": "Ruby", "followers_count": 149, "location": "Kronshangen, Germany"}, {"fullname": "Duncan Coutts", "public_repo_count": 11, "score": 1.0, "repos": 11, "username": "dcoutts", "followers": 149, "gravatar_id": "", "created": "2012-01-17T19:29:53Z", "name": "Duncan Coutts", "login": "dcoutts", "id": "user-1339423", "type": "user", "created_at": "2012-01-17T19:29:53Z", "language": "Haskell", "followers_count": 149, "location": null}, {"fullname": "Yacine Rezgui", "public_repo_count": 150, "score": 1.0, "repos": 150, "username": "yrezgui", "followers": 149, "gravatar_id": "", "created": "2011-10-09T12:05:06Z", "name": "Yacine Rezgui", "login": "yrezgui", "id": "user-1113976", "type": "user", "created_at": "2011-10-09T12:05:06Z", "language": "JavaScript", "followers_count": 149, "location": "London, UK"}, {"fullname": "Eric Lewis", "public_repo_count": 172, "score": 1.0, "repos": 172, "username": "ericandrewlewis", "followers": 149, "gravatar_id": "", "created": "2011-09-28T18:13:02Z", "name": "Eric Lewis", "login": "ericandrewlewis", "id": "user-1087646", "type": "user", "created_at": "2011-09-28T18:13:02Z", "language": "JavaScript", "followers_count": 149, "location": "New York, NY"}, {"fullname": "MyFlashLabs", "public_repo_count": 38, "score": 1.0, "repos": 38, "username": "myflashlab", "followers": 149, "gravatar_id": "", "created": "2012-04-30T15:53:05Z", "name": "MyFlashLabs", "login": "myflashlab", "id": "user-1692948", "type": "user", "created_at": "2012-04-30T15:53:05Z", "language": "ActionScript", "followers_count": 149, "location": null}, {"fullname": "Devin Walters", "public_repo_count": 211, "score": 1.0, "repos": 211, "username": "devn", "followers": 149, "gravatar_id": "", "created": "2008-05-15T18:58:51Z", "name": "Devin Walters", "login": "devn", "id": "user-10421", "type": "user", "created_at": "2008-05-15T18:58:51Z", "language": "Clojure", "followers_count": 149, "location": "Madison, WI"}, {"fullname": "Juan Blanco", "public_repo_count": 114, "score": 1.0, "repos": 114, "username": "juanfranblanco", "followers": 149, "gravatar_id": "", "created": "2011-01-13T09:44:10Z", "name": "Juan Blanco", "login": "juanfranblanco", "id": "user-562371", "type": "user", "created_at": "2011-01-13T09:44:10Z", "language": "C#", "followers_count": 149, "location": "United Kingdom"}, {"fullname": "Zack Bloom", "public_repo_count": 75, "score": 1.0, "repos": 75, "username": "zackbloom", "followers": 149, "gravatar_id": "", "created": "2009-02-17T21:08:45Z", "name": "Zack Bloom", "login": "zackbloom", "id": "user-55347", "type": "user", "created_at": "2009-02-17T21:08:45Z", "language": "JavaScript", "followers_count": 149, "location": "Boston"}, {"fullname": "Sjors Provoost", "public_repo_count": 76, "score": 1.0, "repos": 76, "username": "Sjors", "followers": 149, "gravatar_id": "", "created": "2008-05-14T01:20:21Z", "name": "Sjors Provoost", "login": "Sjors", "id": "user-10217", "type": "user", "created_at": "2008-05-14T01:20:21Z", "language": "Ruby", "followers_count": 149, "location": "Utrecht, The Netherlands"}, {"fullname": "Fabian K\u00f6nig", "public_repo_count": 2, "score": 1.0, "repos": 2, "username": "Fabi", "followers": 149, "gravatar_id": "", "created": "2010-04-18T16:22:50Z", "name": "Fabian K\u00f6nig", "login": "Fabi", "id": "user-246718", "type": "user", "created_at": "2010-04-18T16:22:50Z", "language": "C#", "followers_count": 149, "location": "Germany"}]}