{"users": [{"fullname": "Jordan Kasper", "public_repo_count": 78, "score": 1.0, "repos": 78, "username": "jakerella", "followers": 145, "gravatar_id": "", "created": "2010-10-22T17:16:03Z", "name": "Jordan Kasper", "login": "jakerella", "id": "user-450036", "type": "user", "created_at": "2010-10-22T17:16:03Z", "language": "JavaScript", "followers_count": 145, "location": "Washington, DC"}, {"fullname": "Tomohiro Taira", "public_repo_count": 78, "score": 1.0, "repos": 78, "username": "Tomohiro", "followers": 145, "gravatar_id": "", "created": "2009-02-13T13:17:16Z", "name": "Tomohiro Taira", "login": "Tomohiro", "id": "user-54254", "type": "user", "created_at": "2009-02-13T13:17:16Z", "language": "Ruby", "followers_count": 145, "location": "Okinawa, JAPAN"}, {"fullname": "Kaz Sato", "public_repo_count": 19, "score": 1.0, "repos": 19, "username": "kazunori279", "followers": 145, "gravatar_id": "", "created": "2012-04-08T12:21:14Z", "name": "Kaz Sato", "login": "kazunori279", "id": "user-1623040", "type": "user", "created_at": "2012-04-08T12:21:14Z", "language": "Python", "followers_count": 145, "location": "Tokyo, Japan"}, {"fullname": "Jesse Luehrs", "public_repo_count": 275, "score": 1.0, "repos": 275, "username": "doy", "followers": 145, "gravatar_id": "", "created": "2009-04-27T23:02:20Z", "name": "Jesse Luehrs", "login": "doy", "id": "user-78547", "type": "user", "created_at": "2009-04-27T23:02:20Z", "language": "Perl", "followers_count": 145, "location": null}, {"fullname": "Hugo Duncan", "public_repo_count": 153, "score": 1.0, "repos": 153, "username": "hugoduncan", "followers": 145, "gravatar_id": "", "created": "2009-02-12T20:12:54Z", "name": "Hugo Duncan", "login": "hugoduncan", "id": "user-54043", "type": "user", "created_at": "2009-02-12T20:12:54Z", "language": "Clojure", "followers_count": 145, "location": null}, {"fullname": "Patrick Lauber", "public_repo_count": 26, "score": 1.0, "repos": 26, "username": "digi604", "followers": 145, "gravatar_id": "", "created": "2008-09-20T12:59:31Z", "name": "Patrick Lauber", "login": "digi604", "id": "user-25490", "type": "user", "created_at": "2008-09-20T12:59:31Z", "language": "Python", "followers_count": 145, "location": "Z\u00fcrich, Switzerland"}, {"fullname": "Darron Eggins", "public_repo_count": 2, "score": 1.0, "repos": 2, "username": "eggins", "followers": 145, "gravatar_id": "", "created": "2014-10-14T23:45:36Z", "name": "Darron Eggins", "login": "eggins", "id": "user-9223690", "type": "user", "created_at": "2014-10-14T23:45:36Z", "language": "Python", "followers_count": 145, "location": "Gold Coast"}, {"fullname": "Asim Shankar", "public_repo_count": 12, "score": 1.0, "repos": 12, "username": "asimshankar", "followers": 145, "gravatar_id": "", "created": "2008-07-04T09:30:25Z", "name": "Asim Shankar", "login": "asimshankar", "id": "user-16018", "type": "user", "created_at": "2008-07-04T09:30:25Z", "language": "Go", "followers_count": 145, "location": null}, {"fullname": "Aiden Scandella", "public_repo_count": 77, "score": 1.0, "repos": 77, "username": "sectioneight", "followers": 145, "gravatar_id": "", "created": "2009-06-19T16:52:41Z", "name": "Aiden Scandella", "login": "sectioneight", "id": "user-97087", "type": "user", "created_at": "2009-06-19T16:52:41Z", "language": "Ruby", "followers_count": 145, "location": "Seattle"}, {"fullname": "Bohan Zhang", "public_repo_count": 75, "score": 1.0, "repos": 75, "username": "ZhangBohan", "followers": 145, "gravatar_id": "", "created": "2012-09-10T12:44:13Z", "name": "Bohan Zhang", "login": "ZhangBohan", "id": "user-2317407", "type": "user", "created_at": "2012-09-10T12:44:13Z", "language": "Python", "followers_count": 145, "location": "China"}, {"fullname": "Ross Flieger-Allison", "public_repo_count": 11, "score": 1.0, "repos": 11, "username": "rfliegerallison", "followers": 145, "gravatar_id": "", "created": "2014-01-26T22:08:11Z", "name": "Ross Flieger-Allison", "login": "rfliegerallison", "id": "user-6509399", "type": "user", "created_at": "2014-01-26T22:08:11Z", "language": "Python", "followers_count": 145, "location": "Somerville, MA"}, {"fullname": "Liyun", "public_repo_count": 14, "score": 1.0, "repos": 14, "username": "cloudly", "followers": 145, "gravatar_id": "", "created": "2010-01-01T16:11:00Z", "name": "Liyun", "login": "cloudly", "id": "user-175005", "type": "user", "created_at": "2010-01-01T16:11:00Z", "language": "R", "followers_count": 145, "location": "San Jose, CA"}, {"fullname": "Moses Nakamura", "public_repo_count": 112, "score": 1.0, "repos": 112, "username": "mosesn", "followers": 145, "gravatar_id": "", "created": "2009-11-22T02:52:41Z", "name": "Moses Nakamura", "login": "mosesn", "id": "user-156562", "type": "user", "created_at": "2009-11-22T02:52:41Z", "language": "Scala", "followers_count": 145, "location": "SF"}, {"fullname": "Max Gorin", "public_repo_count": 23, "score": 1.0, "repos": 23, "username": "mxgrn", "followers": 145, "gravatar_id": "", "created": "2008-11-11T22:33:04Z", "name": "Max Gorin", "login": "mxgrn", "id": "user-33935", "type": "user", "created_at": "2008-11-11T22:33:04Z", "language": "Ruby", "followers_count": 145, "location": "Impromptu"}, {"fullname": "Coen Jacobs", "public_repo_count": 29, "score": 1.0, "repos": 29, "username": "coenjacobs", "followers": 145, "gravatar_id": "", "created": "2010-04-16T19:31:54Z", "name": "Coen Jacobs", "login": "coenjacobs", "id": "user-245703", "type": "user", "created_at": "2010-04-16T19:31:54Z", "language": "PHP", "followers_count": 145, "location": "Bladel, The Netherlands"}, {"fullname": "Michael Keller", "public_repo_count": 160, "score": 1.0, "repos": 160, "username": "mhkeller", "followers": 145, "gravatar_id": "", "created": "2010-11-27T06:09:57Z", "name": "Michael Keller", "login": "mhkeller", "id": "user-498744", "type": "user", "created_at": "2010-11-27T06:09:57Z", "language": "JavaScript", "followers_count": 145, "location": "New York, NY"}, {"fullname": "Shannon Potter", "public_repo_count": 3, "score": 1.0, "repos": 3, "username": "LucasTizma", "followers": 145, "gravatar_id": "", "created": "2009-03-24T15:38:16Z", "name": "Shannon Potter", "login": "LucasTizma", "id": "user-66559", "type": "user", "created_at": "2009-03-24T15:38:16Z", "language": "HTML", "followers_count": 145, "location": "San Francisco, CA"}, {"fullname": "Jason Brennan", "public_repo_count": 73, "score": 1.0, "repos": 73, "username": "jbrennan", "followers": 145, "gravatar_id": "", "created": "2009-09-27T17:52:03Z", "name": "Jason Brennan", "login": "jbrennan", "id": "user-131923", "type": "user", "created_at": "2009-09-27T17:52:03Z", "language": "Objective-C", "followers_count": 145, "location": "Brooklyn, USA"}, {"fullname": "Leo Natan", "public_repo_count": 22, "score": 1.0, "repos": 22, "username": "LeoNatan", "followers": 145, "gravatar_id": "", "created": "2012-09-03T11:34:21Z", "name": "Leo Natan", "login": "LeoNatan", "id": "user-2270433", "type": "user", "created_at": "2012-09-03T11:34:21Z", "language": "Objective-C", "followers_count": 145, "location": "Tel Aviv, Israel"}, {"fullname": "Viljami Kuosmanen", "public_repo_count": 69, "score": 1.0, "repos": 69, "username": "anttiviljami", "followers": 145, "gravatar_id": "", "created": "2013-12-04T14:30:10Z", "name": "Viljami Kuosmanen", "login": "anttiviljami", "id": "user-6105650", "type": "user", "created_at": "2013-12-04T14:30:10Z", "language": "PHP", "followers_count": 145, "location": "Tampere, Finland"}, {"fullname": "", "public_repo_count": 21, "score": 1.0, "repos": 21, "username": "iBearcat", "followers": 145, "gravatar_id": "", "created": "2016-10-01T09:59:33Z", "name": "", "login": "iBearcat", "id": "user-22558737", "type": "user", "created_at": "2016-10-01T09:59:33Z", "language": "Java", "followers_count": 145, "location": "China"}, {"fullname": "Xi Qi", "public_repo_count": 22, "score": 1.0, "repos": 22, "username": "macdao", "followers": 145, "gravatar_id": "", "created": "2012-01-07T08:28:06Z", "name": "Xi Qi", "login": "macdao", "id": "user-1311124", "type": "user", "created_at": "2012-01-07T08:28:06Z", "language": "Java", "followers_count": 145, "location": "Shanghai, China"}, {"fullname": "Gokhan Moral", "public_repo_count": 12, "score": 1.0, "repos": 12, "username": "gokhanmoral", "followers": 145, "gravatar_id": "", "created": "2012-01-27T22:35:00Z", "name": "Gokhan Moral", "login": "gokhanmoral", "id": "user-1386203", "type": "user", "created_at": "2012-01-27T22:35:00Z", "language": "C", "followers_count": 145, "location": "Ankara / Turkey"}, {"fullname": "Roy Macdonald", "public_repo_count": 67, "score": 1.0, "repos": 67, "username": "roymacdonald", "followers": 145, "gravatar_id": "", "created": "2011-08-11T21:41:38Z", "name": "Roy Macdonald", "login": "roymacdonald", "id": "user-974878", "type": "user", "created_at": "2011-08-11T21:41:38Z", "language": "C++", "followers_count": 145, "location": "Santiago, Chile"}, {"fullname": "Damian Schenkelman", "public_repo_count": 87, "score": 1.0, "repos": 87, "username": "dschenkelman", "followers": 145, "gravatar_id": "", "created": "2013-01-25T02:57:55Z", "name": "Damian Schenkelman", "login": "dschenkelman", "id": "user-3376731", "type": "user", "created_at": "2013-01-25T02:57:55Z", "language": "JavaScript", "followers_count": 145, "location": null}, {"fullname": "Eric Lombrozo", "public_repo_count": 54, "score": 1.0, "repos": 54, "username": "CodeShark", "followers": 145, "gravatar_id": "", "created": "2011-07-04T18:15:25Z", "name": "Eric Lombrozo", "login": "CodeShark", "id": "user-894059", "type": "user", "created_at": "2011-07-04T18:15:25Z", "language": "C++", "followers_count": 145, "location": ""}, {"fullname": "Christoph Feichtenhofer", "public_repo_count": 10, "score": 1.0, "repos": 10, "username": "feichtenhofer", "followers": 145, "gravatar_id": "", "created": "2014-06-07T14:31:02Z", "name": "Christoph Feichtenhofer", "login": "feichtenhofer", "id": "user-7824925", "type": "user", "created_at": "2014-06-07T14:31:02Z", "language": "Cuda", "followers_count": 145, "location": "Austria"}, {"fullname": "Tyrone Nicholas", "public_repo_count": 9, "score": 1.0, "repos": 9, "username": "tyronen", "followers": 145, "gravatar_id": "", "created": "2011-08-04T09:15:59Z", "name": "Tyrone Nicholas", "login": "tyronen", "id": "user-958570", "type": "user", "created_at": "2011-08-04T09:15:59Z", "language": "Java", "followers_count": 145, "location": "London, United Kingdom"}, {"fullname": "Kefu Chai", "public_repo_count": 51, "score": 1.0, "repos": 51, "username": "tchaikov", "followers": 145, "gravatar_id": "", "created": "2009-03-01T12:18:40Z", "name": "Kefu Chai", "login": "tchaikov", "id": "user-59071", "type": "user", "created_at": "2009-03-01T12:18:40Z", "language": "Python", "followers_count": 145, "location": "shanghai"}, {"fullname": "Jacob Cook", "public_repo_count": 24, "score": 1.0, "repos": 24, "username": "peakwinter", "followers": 145, "gravatar_id": "", "created": "2011-08-22T19:56:52Z", "name": "Jacob Cook", "login": "peakwinter", "id": "user-997174", "type": "user", "created_at": "2011-08-22T19:56:52Z", "language": "Python", "followers_count": 145, "location": "Montreal, Quebec"}, {"fullname": "Davis Kim", "public_repo_count": 64, "score": 1.0, "repos": 64, "username": "davis", "followers": 145, "gravatar_id": "", "created": "2013-06-27T20:22:24Z", "name": "Davis Kim", "login": "davis", "id": "user-4855619", "type": "user", "created_at": "2013-06-27T20:22:24Z", "language": "JavaScript", "followers_count": 145, "location": "San Francisco"}, {"fullname": "Howard Butler", "public_repo_count": 43, "score": 1.0, "repos": 43, "username": "hobu", "followers": 145, "gravatar_id": "", "created": "2009-05-23T05:44:12Z", "name": "Howard Butler", "login": "hobu", "id": "user-87751", "type": "user", "created_at": "2009-05-23T05:44:12Z", "language": "C++", "followers_count": 145, "location": "Iowa City, IA"}, {"fullname": "Artur Termenji", "public_repo_count": 38, "score": 1.0, "repos": 38, "username": "atermenji", "followers": 145, "gravatar_id": "", "created": "2011-11-11T09:15:29Z", "name": "Artur Termenji", "login": "atermenji", "id": "user-1188140", "type": "user", "created_at": "2011-11-11T09:15:29Z", "language": "Java", "followers_count": 145, "location": "Kiev, Ukraine"}, {"fullname": null, "public_repo_count": 32, "score": 1.0, "repos": 32, "username": "karliekloss", "followers": 145, "gravatar_id": "", "created": "2014-08-24T02:47:22Z", "name": null, "login": "karliekloss", "id": "user-8534616", "type": "user", "created_at": "2014-08-24T02:47:22Z", "language": "Ruby", "followers_count": 145, "location": null}, {"fullname": "goodboy", "public_repo_count": 35, "score": 1.0, "repos": 35, "username": "xyxiao001", "followers": 145, "gravatar_id": "", "created": "2015-11-06T02:16:58Z", "name": "goodboy", "login": "xyxiao001", "id": "user-15681693", "type": "user", "created_at": "2015-11-06T02:16:58Z", "language": "JavaScript", "followers_count": 145, "location": "china"}, {"fullname": "Choi Gunho", "public_repo_count": 27, "score": 1.0, "repos": 27, "username": "GunhoChoi", "followers": 145, "gravatar_id": "", "created": "2016-03-03T06:47:19Z", "name": "Choi Gunho", "login": "GunhoChoi", "id": "user-17610397", "type": "user", "created_at": "2016-03-03T06:47:19Z", "language": "Python", "followers_count": 145, "location": "Seoul, Republic of Korea"}, {"fullname": "Sergio Brito", "public_repo_count": 42, "score": 1.0, "repos": 42, "username": "yacafx", "followers": 145, "gravatar_id": "", "created": "2009-11-02T12:06:31Z", "name": "Sergio Brito", "login": "yacafx", "id": "user-147724", "type": "user", "created_at": "2009-11-02T12:06:31Z", "language": "JavaScript", "followers_count": 145, "location": "Mexico"}, {"fullname": "Mike Tsao", "public_repo_count": 84, "score": 1.0, "repos": 84, "username": "sowbug", "followers": 145, "gravatar_id": "", "created": "2008-10-22T01:46:53Z", "name": "Mike Tsao", "login": "sowbug", "id": "user-30292", "type": "user", "created_at": "2008-10-22T01:46:53Z", "language": "JavaScript", "followers_count": 145, "location": "Silicon Valley, California"}, {"fullname": "Pieter Vanderwerff", "public_repo_count": 34, "score": 1.0, "repos": 34, "username": "pieterv", "followers": 145, "gravatar_id": "", "created": "2010-10-13T20:18:59Z", "name": "Pieter Vanderwerff", "login": "pieterv", "id": "user-438482", "type": "user", "created_at": "2010-10-13T20:18:59Z", "language": "JavaScript", "followers_count": 145, "location": null}, {"fullname": "\u6881\u6d77 Liang Hai", "public_repo_count": 2, "score": 1.0, "repos": 2, "username": "lianghai", "followers": 145, "gravatar_id": "", "created": "2010-07-25T05:52:44Z", "name": "\u6881\u6d77 Liang Hai", "login": "lianghai", "id": "user-343259", "type": "user", "created_at": "2010-07-25T05:52:44Z", "language": null, "followers_count": 145, "location": "Beijing, China"}, {"fullname": "cofface", "public_repo_count": 21, "score": 1.0, "repos": 21, "username": "cofface", "followers": 145, "gravatar_id": "", "created": "2013-03-27T00:44:15Z", "name": "cofface", "login": "cofface", "id": "user-3980360", "type": "user", "created_at": "2013-03-27T00:44:15Z", "language": "C", "followers_count": 145, "location": null}, {"fullname": "Karl Dubost", "public_repo_count": 71, "score": 1.0, "repos": 71, "username": "karlcow", "followers": 145, "gravatar_id": "", "created": "2010-12-01T16:33:25Z", "name": "Karl Dubost", "login": "karlcow", "id": "user-505230", "type": "user", "created_at": "2010-12-01T16:33:25Z", "language": "Python", "followers_count": 145, "location": "Tokyo, Japan"}, {"fullname": "Eaton", "public_repo_count": 41, "score": 1.0, "repos": 41, "username": "eaton", "followers": 145, "gravatar_id": "", "created": "2009-01-14T05:04:14Z", "name": "Eaton", "login": "eaton", "id": "user-46423", "type": "user", "created_at": "2009-01-14T05:04:14Z", "language": "PHP", "followers_count": 145, "location": "Chicago"}, {"fullname": "Jonathan Gros-Dubois", "public_repo_count": 34, "score": 1.0, "repos": 34, "username": "jondubois", "followers": 145, "gravatar_id": "", "created": "2011-11-10T23:34:28Z", "name": "Jonathan Gros-Dubois", "login": "jondubois", "id": "user-1187447", "type": "user", "created_at": "2011-11-10T23:34:28Z", "language": "JavaScript", "followers_count": 145, "location": "Berlin, Germany"}, {"fullname": "Yuji Nakayama", "public_repo_count": 58, "score": 1.0, "repos": 58, "username": "yujinakayama", "followers": 145, "gravatar_id": "", "created": "2009-05-12T13:02:12Z", "name": "Yuji Nakayama", "login": "yujinakayama", "id": "user-83656", "type": "user", "created_at": "2009-05-12T13:02:12Z", "language": "Ruby", "followers_count": 145, "location": "Tokyo, Japan"}, {"fullname": "", "public_repo_count": 32, "score": 1.0, "repos": 32, "username": "wdullaer", "followers": 145, "gravatar_id": "", "created": "2014-01-02T17:39:54Z", "name": "", "login": "wdullaer", "id": "user-6305221", "type": "user", "created_at": "2014-01-02T17:39:54Z", "language": "JavaScript", "followers_count": 145, "location": null}, {"fullname": "Leon Jacobs", "public_repo_count": 31, "score": 1.0, "repos": 31, "username": "leonjza", "followers": 145, "gravatar_id": "", "created": "2011-10-24T12:42:32Z", "name": "Leon Jacobs", "login": "leonjza", "id": "user-1148127", "type": "user", "created_at": "2011-10-24T12:42:32Z", "language": "Python", "followers_count": 145, "location": "South Africa"}, {"fullname": "Mathieu Bolard", "public_repo_count": 42, "score": 1.0, "repos": 42, "username": "mattlawer", "followers": 145, "gravatar_id": "", "created": "2010-01-11T21:22:00Z", "name": "Mathieu Bolard", "login": "mattlawer", "id": "user-180296", "type": "user", "created_at": "2010-01-11T21:22:00Z", "language": "Objective-C", "followers_count": 145, "location": "France"}, {"fullname": "Yoichiro Tanaka", "public_repo_count": 44, "score": 1.0, "repos": 44, "username": "yoichiro", "followers": 145, "gravatar_id": "", "created": "2010-05-02T08:05:57Z", "name": "Yoichiro Tanaka", "login": "yoichiro", "id": "user-261787", "type": "user", "created_at": "2010-05-02T08:05:57Z", "language": "JavaScript", "followers_count": 145, "location": "Tokyo, Japan"}, {"fullname": "Erik de Castro Lopo", "public_repo_count": 152, "score": 1.0, "repos": 152, "username": "erikd", "followers": 145, "gravatar_id": "", "created": "2010-06-17T01:50:30Z", "name": "Erik de Castro Lopo", "login": "erikd", "id": "user-307277", "type": "user", "created_at": "2010-06-17T01:50:30Z", "language": "Haskell", "followers_count": 145, "location": "Australia"}, {"fullname": "Mark Sonnabaum", "public_repo_count": 88, "score": 1.0, "repos": 88, "username": "msonnabaum", "followers": 145, "gravatar_id": "", "created": "2009-01-27T22:56:40Z", "name": "Mark Sonnabaum", "login": "msonnabaum", "id": "user-49792", "type": "user", "created_at": "2009-01-27T22:56:40Z", "language": "Ruby", "followers_count": 145, "location": "Denton, TX"}, {"fullname": "Matt Ingenthron", "public_repo_count": 57, "score": 1.0, "repos": 57, "username": "ingenthr", "followers": 145, "gravatar_id": "", "created": "2009-05-05T17:38:10Z", "name": "Matt Ingenthron", "login": "ingenthr", "id": "user-81302", "type": "user", "created_at": "2009-05-05T17:38:10Z", "language": "Java", "followers_count": 145, "location": "Orange County, CA, USA"}, {"fullname": "fREW Schmidt", "public_repo_count": 316, "score": 1.0, "repos": 316, "username": "frioux", "followers": 145, "gravatar_id": "", "created": "2008-04-22T14:05:21Z", "name": "fREW Schmidt", "login": "frioux", "id": "user-8163", "type": "user", "created_at": "2008-04-22T14:05:21Z", "language": "Perl", "followers_count": 145, "location": "Santa Monica, CA"}, {"fullname": "Oddvar Moe", "public_repo_count": 56, "score": 1.0, "repos": 56, "username": "api0cradle", "followers": 145, "gravatar_id": "", "created": "2015-06-22T09:06:28Z", "name": "Oddvar Moe", "login": "api0cradle", "id": "user-12997471", "type": "user", "created_at": "2015-06-22T09:06:28Z", "language": "PowerShell", "followers_count": 145, "location": null}, {"fullname": "Ming Chow", "public_repo_count": 10, "score": 1.0, "repos": 10, "username": "mchow01", "followers": 145, "gravatar_id": "", "created": "2010-09-05T22:00:41Z", "name": "Ming Chow", "login": "mchow01", "id": "user-388704", "type": "user", "created_at": "2010-09-05T22:00:41Z", "language": "JavaScript", "followers_count": 145, "location": "Medford, MA"}, {"fullname": "Robert Chiniquy", "public_repo_count": 78, "score": 1.0, "repos": 78, "username": "robert-chiniquy", "followers": 145, "gravatar_id": "", "created": "2011-02-17T18:56:05Z", "name": "Robert Chiniquy", "login": "robert-chiniquy", "id": "user-623808", "type": "user", "created_at": "2011-02-17T18:56:05Z", "language": "JavaScript", "followers_count": 145, "location": "Eas{t,y} Bay"}, {"fullname": "Androxyde", "public_repo_count": 5, "score": 1.0, "repos": 5, "username": "Androxyde", "followers": 145, "gravatar_id": "", "created": "2011-10-07T16:24:44Z", "name": "Androxyde", "login": "Androxyde", "id": "user-1110635", "type": "user", "created_at": "2011-10-07T16:24:44Z", "language": "Java", "followers_count": 145, "location": null}, {"fullname": "Preet", "public_repo_count": 22, "score": 1.0, "repos": 22, "username": "pshihn", "followers": 145, "gravatar_id": "", "created": "2011-06-06T23:48:42Z", "name": "Preet", "login": "pshihn", "id": "user-833927", "type": "user", "created_at": "2011-06-06T23:48:42Z", "language": "CSS", "followers_count": 145, "location": "San Francisco"}, {"fullname": "Ian Collins", "public_repo_count": 28, "score": 1.0, "repos": 28, "username": "3n", "followers": 145, "gravatar_id": "", "created": "2008-04-12T02:40:11Z", "name": "Ian Collins", "login": "3n", "id": "user-6855", "type": "user", "created_at": "2008-04-12T02:40:11Z", "language": "JavaScript", "followers_count": 145, "location": "Portland"}, {"fullname": "Johannes Rieken", "public_repo_count": 38, "score": 1.0, "repos": 38, "username": "jrieken", "followers": 145, "gravatar_id": "", "created": "2012-05-30T15:16:06Z", "name": "Johannes Rieken", "login": "jrieken", "id": "user-1794099", "type": "user", "created_at": "2012-05-30T15:16:06Z", "language": "JavaScript", "followers_count": 145, "location": "Switzerland"}, {"fullname": "Carlos Cuesta", "public_repo_count": 16, "score": 1.0, "repos": 16, "username": "carloscuesta", "followers": 145, "gravatar_id": "", "created": "2014-05-19T10:53:24Z", "name": "Carlos Cuesta", "login": "carloscuesta", "id": "user-7629661", "type": "user", "created_at": "2014-05-19T10:53:24Z", "language": "JavaScript", "followers_count": 145, "location": "Barcelona"}, {"fullname": "Tom Ritter", "public_repo_count": 57, "score": 1.0, "repos": 57, "username": "tomrittervg", "followers": 145, "gravatar_id": "", "created": "2009-12-06T23:49:45Z", "name": "Tom Ritter", "login": "tomrittervg", "id": "user-163497", "type": "user", "created_at": "2009-12-06T23:49:45Z", "language": "Python", "followers_count": 145, "location": null}, {"fullname": "UFreedom", "public_repo_count": 19, "score": 1.0, "repos": 19, "username": "UFreedom", "followers": 145, "gravatar_id": "", "created": "2013-08-01T22:41:36Z", "name": "UFreedom", "login": "UFreedom", "id": "user-5142436", "type": "user", "created_at": "2013-08-01T22:41:36Z", "language": "Java", "followers_count": 145, "location": "Beijing.China"}, {"fullname": "Sudhanshu Yadav", "public_repo_count": 37, "score": 1.0, "repos": 37, "username": "s-yadav", "followers": 145, "gravatar_id": "", "created": "2012-12-21T08:53:48Z", "name": "Sudhanshu Yadav", "login": "s-yadav", "id": "user-3096766", "type": "user", "created_at": "2012-12-21T08:53:48Z", "language": "JavaScript", "followers_count": 145, "location": "Bangalore, India"}, {"fullname": "codeutnfra", "public_repo_count": 2, "score": 1.0, "repos": 2, "username": "codeutnfra", "followers": 145, "gravatar_id": "", "created": "2016-09-15T13:52:43Z", "name": "codeutnfra", "login": "codeutnfra", "id": "user-22218496", "type": "user", "created_at": "2016-09-15T13:52:43Z", "language": "C", "followers_count": 145, "location": "Av Mitre 450, Avellaneda, Buenos Aires, Argentina"}, {"fullname": "qntm", "public_repo_count": 30, "score": 1.0, "repos": 30, "username": "qntm", "followers": 145, "gravatar_id": "", "created": "2012-05-13T19:57:36Z", "name": "qntm", "login": "qntm", "id": "user-1735353", "type": "user", "created_at": "2012-05-13T19:57:36Z", "language": "JavaScript", "followers_count": 145, "location": null}, {"fullname": "", "public_repo_count": 7, "score": 1.0, "repos": 7, "username": "bigfa", "followers": 145, "gravatar_id": "", "created": "2012-12-19T06:37:27Z", "name": "", "login": "bigfa", "id": "user-3078516", "type": "user", "created_at": "2012-12-19T06:37:27Z", "language": "PHP", "followers_count": 145, "location": "China"}, {"fullname": "Daniel Kennett", "public_repo_count": 39, "score": 1.0, "repos": 39, "username": "iKenndac", "followers": 145, "gravatar_id": "", "created": "2010-12-08T16:19:19Z", "name": "Daniel Kennett", "login": "iKenndac", "id": "user-514900", "type": "user", "created_at": "2010-12-08T16:19:19Z", "language": "Objective-C", "followers_count": 145, "location": "Stockholm, Sweden"}]}