{"users": [{"fullname": "Shinichi Tomita", "public_repo_count": 55, "score": 1.0, "repos": 55, "username": "stomita", "followers": 156, "gravatar_id": "", "created": "2008-09-06T02:40:27Z", "name": "Shinichi Tomita", "login": "stomita", "id": "user-23387", "type": "user", "created_at": "2008-09-06T02:40:27Z", "language": "JavaScript", "followers_count": 156, "location": "Tokyo, Japan"}, {"fullname": null, "public_repo_count": 0, "score": 1.0, "repos": 0, "username": "chengangkk", "followers": 156, "gravatar_id": "", "created": "2013-06-18T01:56:02Z", "name": null, "login": "chengangkk", "id": "user-4724028", "type": "user", "created_at": "2013-06-18T01:56:02Z", "language": null, "followers_count": 156, "location": null}, {"fullname": "David Zhang", "public_repo_count": 9, "score": 1.0, "repos": 9, "username": "daqing", "followers": 156, "gravatar_id": "", "created": "2008-04-22T04:48:40Z", "name": "David Zhang", "login": "daqing", "id": "user-8126", "type": "user", "created_at": "2008-04-22T04:48:40Z", "language": "Ruby", "followers_count": 156, "location": "Shandong, China"}, {"fullname": "Simon Eisenmann", "public_repo_count": 69, "score": 1.0, "repos": 69, "username": "longsleep", "followers": 156, "gravatar_id": "", "created": "2012-04-22T11:57:09Z", "name": "Simon Eisenmann", "login": "longsleep", "id": "user-1667797", "type": "user", "created_at": "2012-04-22T11:57:09Z", "language": "C", "followers_count": 156, "location": "Stuttgart"}, {"fullname": "John Wang", "public_repo_count": 81, "score": 1.0, "repos": 81, "username": "jwang", "followers": 156, "gravatar_id": "", "created": "2009-04-15T23:25:18Z", "name": "John Wang", "login": "jwang", "id": "user-74253", "type": "user", "created_at": "2009-04-15T23:25:18Z", "language": "Ruby", "followers_count": 156, "location": "Cupertino, CA"}, {"fullname": "Ian Dunn", "public_repo_count": 43, "score": 1.0, "repos": 43, "username": "iandunn", "followers": 156, "gravatar_id": "", "created": "2010-11-16T16:07:15Z", "name": "Ian Dunn", "login": "iandunn", "id": "user-484068", "type": "user", "created_at": "2010-11-16T16:07:15Z", "language": "PHP", "followers_count": 156, "location": "Seattle"}, {"fullname": "vic", "public_repo_count": 15, "score": 1.0, "repos": 15, "username": "coneycode", "followers": 156, "gravatar_id": "", "created": "2012-09-18T10:22:05Z", "name": "vic", "login": "coneycode", "id": "user-2369316", "type": "user", "created_at": "2012-09-18T10:22:05Z", "language": "JavaScript", "followers_count": 156, "location": "\u4e2d\u56fd"}, {"fullname": "Lane", "public_repo_count": 13, "score": 1.0, "repos": 13, "username": "lixuancn", "followers": 156, "gravatar_id": "", "created": "2014-01-10T12:31:50Z", "name": "Lane", "login": "lixuancn", "id": "user-6368760", "type": "user", "created_at": "2014-01-10T12:31:50Z", "language": "Go", "followers_count": 156, "location": "Bei Jing"}, {"fullname": "dong", "public_repo_count": 28, "score": 1.0, "repos": 28, "username": "dxq613", "followers": 156, "gravatar_id": "", "created": "2011-12-15T04:39:00Z", "name": "dong", "login": "dxq613", "id": "user-1264678", "type": "user", "created_at": "2011-12-15T04:39:00Z", "language": "JavaScript", "followers_count": 156, "location": "hangzhou china"}, {"fullname": "Jbee", "public_repo_count": 79, "score": 1.0, "repos": 79, "username": "JaeYeopHan", "followers": 156, "gravatar_id": "", "created": "2016-03-18T09:13:22Z", "name": "Jbee", "login": "JaeYeopHan", "id": "user-17924127", "type": "user", "created_at": "2016-03-18T09:13:22Z", "language": "JavaScript", "followers_count": 156, "location": "\uacbd\uae30\ub3c4 \uc131\ub0a8\uc2dc"}, {"fullname": "Breno Polanski", "public_repo_count": 252, "score": 1.0, "repos": 252, "username": "brenopolanski", "followers": 156, "gravatar_id": "", "created": "2012-06-26T13:23:08Z", "name": "Breno Polanski", "login": "brenopolanski", "id": "user-1894191", "type": "user", "created_at": "2012-06-26T13:23:08Z", "language": "JavaScript", "followers_count": 156, "location": "Brazil"}]}