{"users": [{"fullname": "Daniel Steigerwald", "public_repo_count": 9, "score": 1.0, "repos": 9, "username": "steida", "followers": 403, "gravatar_id": "", "created": "2009-03-23T23:30:16Z", "name": "Daniel Steigerwald", "login": "steida", "id": "user-66249", "type": "user", "created_at": "2009-03-23T23:30:16Z", "language": "JavaScript", "followers_count": 403, "location": "Czech, Prague"}, {"fullname": "Daniel Dunbar", "public_repo_count": 16, "score": 1.0, "repos": 16, "username": "ddunbar", "followers": 403, "gravatar_id": "", "created": "2009-07-19T20:34:30Z", "name": "Daniel Dunbar", "login": "ddunbar", "id": "user-106625", "type": "user", "created_at": "2009-07-19T20:34:30Z", "language": "Python", "followers_count": 403, "location": "San Francisco, CA"}, {"fullname": "Andrews Sobral", "public_repo_count": 45, "score": 1.0, "repos": 45, "username": "andrewssobral", "followers": 403, "gravatar_id": "", "created": "2010-11-16T01:01:53Z", "name": "Andrews Sobral", "login": "andrewssobral", "id": "user-483114", "type": "user", "created_at": "2010-11-16T01:01:53Z", "language": "Matlab", "followers_count": 403, "location": "Paris, France"}, {"fullname": "Aaron Stacy", "public_repo_count": 104, "score": 1.0, "repos": 104, "username": "aaronj1335", "followers": 403, "gravatar_id": "", "created": "2011-05-13T23:14:21Z", "name": "Aaron Stacy", "login": "aaronj1335", "id": "user-787066", "type": "user", "created_at": "2011-05-13T23:14:21Z", "language": "JavaScript", "followers_count": 403, "location": "Austin, Texas"}, {"fullname": "Assaf Arkin", "public_repo_count": 36, "score": 1.0, "repos": 36, "username": "assaf", "followers": 403, "gravatar_id": "", "created": "2008-04-04T19:43:48Z", "name": "Assaf Arkin", "login": "assaf", "id": "user-5158", "type": "user", "created_at": "2008-04-04T19:43:48Z", "language": "Ruby", "followers_count": 403, "location": "Bay Area, CA"}, {"fullname": "Rob Figueiredo", "public_repo_count": 56, "score": 1.0, "repos": 56, "username": "robfig", "followers": 402, "gravatar_id": "", "created": "2010-12-25T16:00:52Z", "name": "Rob Figueiredo", "login": "robfig", "id": "user-536325", "type": "user", "created_at": "2010-12-25T16:00:52Z", "language": "Go", "followers_count": 402, "location": null}, {"fullname": "", "public_repo_count": 6, "score": 1.0, "repos": 6, "username": "DarthTon", "followers": 402, "gravatar_id": "", "created": "2016-04-02T10:51:15Z", "name": "", "login": "DarthTon", "id": "user-2190385", "type": "user", "created_at": "2016-04-02T10:51:15Z", "language": "C++", "followers_count": 402, "location": null}, {"fullname": "Yan Zhu", "public_repo_count": 16, "score": 1.0, "repos": 16, "username": "picturepan2", "followers": 402, "gravatar_id": "", "created": "2009-09-13T14:40:34Z", "name": "Yan Zhu", "login": "picturepan2", "id": "user-126385", "type": "user", "created_at": "2009-09-13T14:40:34Z", "language": "HTML", "followers_count": 402, "location": "Shanghai / Seattle"}, {"fullname": "Phil Pl\u00fcckthun", "public_repo_count": 93, "score": 1.0, "repos": 93, "username": "kitten", "followers": 402, "gravatar_id": "", "created": "2012-07-25T16:05:16Z", "name": "Phil Pl\u00fcckthun", "login": "kitten", "id": "user-2041385", "type": "user", "created_at": "2012-07-25T16:05:16Z", "language": "JavaScript", "followers_count": 402, "location": "London"}, {"fullname": "Shaun Lebron", "public_repo_count": 134, "score": 1.0, "repos": 134, "username": "shaunlebron", "followers": 402, "gravatar_id": "", "created": "2009-08-19T00:39:43Z", "name": "Shaun Lebron", "login": "shaunlebron", "id": "user-116838", "type": "user", "created_at": "2009-08-19T00:39:43Z", "language": "Clojure", "followers_count": 402, "location": "Houston"}, {"fullname": "Andrew Arnott", "public_repo_count": 140, "score": 1.0, "repos": 140, "username": "AArnott", "followers": 402, "gravatar_id": "", "created": "2008-03-21T16:24:38Z", "name": "Andrew Arnott", "login": "AArnott", "id": "user-3548", "type": "user", "created_at": "2008-03-21T16:24:38Z", "language": "C#", "followers_count": 402, "location": "Sammamish, WA"}, {"fullname": "Aaron Meurer", "public_repo_count": 153, "score": 1.0, "repos": 153, "username": "asmeurer", "followers": 402, "gravatar_id": "", "created": "2009-04-07T19:11:38Z", "name": "Aaron Meurer", "login": "asmeurer", "id": "user-71486", "type": "user", "created_at": "2009-04-07T19:11:38Z", "language": "Python", "followers_count": 402, "location": "Columbia, SC"}, {"fullname": "\u5b50\u718f", "public_repo_count": 36, "score": 1.0, "repos": 36, "username": "lvzixun", "followers": 402, "gravatar_id": "", "created": "2011-12-24T07:07:48Z", "name": "\u5b50\u718f", "login": "lvzixun", "id": "user-1283355", "type": "user", "created_at": "2011-12-24T07:07:48Z", "language": "C", "followers_count": 402, "location": "guangzhou &  dx3906"}, {"fullname": "Sarah Allen", "public_repo_count": 131, "score": 1.0, "repos": 131, "username": "ultrasaurus", "followers": 401, "gravatar_id": "", "created": "2008-12-21T07:29:48Z", "name": "Sarah Allen", "login": "ultrasaurus", "id": "user-41906", "type": "user", "created_at": "2008-12-21T07:29:48Z", "language": "Ruby", "followers_count": 401, "location": "San Francisco"}, {"fullname": "Volkan Ceylan", "public_repo_count": 16, "score": 1.0, "repos": 16, "username": "volkanceylan", "followers": 401, "gravatar_id": "", "created": "2011-04-26T13:33:27Z", "name": "Volkan Ceylan", "login": "volkanceylan", "id": "user-752470", "type": "user", "created_at": "2011-04-26T13:33:27Z", "language": "JavaScript", "followers_count": 401, "location": "Istanbul"}, {"fullname": "hernan", "public_repo_count": 10, "score": 1.0, "repos": 10, "username": "bodymovin", "followers": 401, "gravatar_id": "", "created": "2015-02-20T20:57:29Z", "name": "hernan", "login": "bodymovin", "id": "user-11096607", "type": "user", "created_at": "2015-02-20T20:57:29Z", "language": "JavaScript", "followers_count": 401, "location": null}, {"fullname": null, "public_repo_count": 15, "score": 1.0, "repos": 15, "username": "LearnByBhanuPratap", "followers": 401, "gravatar_id": "", "created": "2016-09-02T07:21:37Z", "name": null, "login": "LearnByBhanuPratap", "id": "user-21795481", "type": "user", "created_at": "2016-09-02T07:21:37Z", "language": "Java", "followers_count": 401, "location": null}, {"fullname": "Liwei Lin", "public_repo_count": 44, "score": 1.0, "repos": 44, "username": "lw-lin", "followers": 401, "gravatar_id": "", "created": "2015-11-14T05:57:00Z", "name": "Liwei Lin", "login": "lw-lin", "id": "user-15843379", "type": "user", "created_at": "2015-11-14T05:57:00Z", "language": "Java", "followers_count": 401, "location": "Beijing, China"}, {"fullname": "Balaji S. Srinivasan", "public_repo_count": 2, "score": 1.0, "repos": 2, "username": "balajis", "followers": 401, "gravatar_id": "", "created": "2008-05-20T12:48:57Z", "name": "Balaji S. Srinivasan", "login": "balajis", "id": "user-10866", "type": "user", "created_at": "2008-05-20T12:48:57Z", "language": "Ruby", "followers_count": 401, "location": " Stanford, CA"}, {"fullname": "Jeroen Janssens", "public_repo_count": 38, "score": 1.0, "repos": 38, "username": "jeroenjanssens", "followers": 401, "gravatar_id": "", "created": "2012-01-22T17:59:00Z", "name": "Jeroen Janssens", "login": "jeroenjanssens", "id": "user-1368256", "type": "user", "created_at": "2012-01-22T17:59:00Z", "language": "Python", "followers_count": 401, "location": "Rotterdam"}, {"fullname": "Aaron Quinlan", "public_repo_count": 67, "score": 1.0, "repos": 67, "username": "arq5x", "followers": 401, "gravatar_id": "", "created": "2009-04-09T22:23:08Z", "name": "Aaron Quinlan", "login": "arq5x", "id": "user-72291", "type": "user", "created_at": "2009-04-09T22:23:08Z", "language": "Python", "followers_count": 401, "location": "Charlottesville, VA"}, {"fullname": "Elbert Alias", "public_repo_count": 15, "score": 1.0, "repos": 15, "username": "AliasIO", "followers": 401, "gravatar_id": "", "created": "2009-04-24T03:14:23Z", "name": "Elbert Alias", "login": "AliasIO", "id": "user-77259", "type": "user", "created_at": "2009-04-24T03:14:23Z", "language": "JavaScript", "followers_count": 401, "location": "Melbourne, Australia"}, {"fullname": "Jim Liu", "public_repo_count": 92, "score": 1.0, "repos": 92, "username": "JimLiu", "followers": 400, "gravatar_id": "", "created": "2011-03-03T09:18:48Z", "name": "Jim Liu", "login": "JimLiu", "id": "user-648674", "type": "user", "created_at": "2011-03-03T09:18:48Z", "language": "JavaScript", "followers_count": 400, "location": "Chicago, IL"}, {"fullname": "hacke2", "public_repo_count": 78, "score": 1.0, "repos": 78, "username": "hacke2", "followers": 400, "gravatar_id": "", "created": "2014-01-14T14:09:53Z", "name": "hacke2", "login": "hacke2", "id": "user-6399899", "type": "user", "created_at": "2014-01-14T14:09:53Z", "language": "JavaScript", "followers_count": 400, "location": "Hangzhou, China"}, {"fullname": "\u90ed\u5b5d\u661f", "public_repo_count": 59, "score": 1.0, "repos": 59, "username": "guoxiaoxing", "followers": 400, "gravatar_id": "", "created": "2015-01-28T08:18:07Z", "name": "\u90ed\u5b5d\u661f", "login": "guoxiaoxing", "id": "user-10738148", "type": "user", "created_at": "2015-01-28T08:18:07Z", "language": "Java", "followers_count": 400, "location": "\u676d\u5dde"}, {"fullname": "ASCE1885", "public_repo_count": 62, "score": 1.0, "repos": 62, "username": "ASCE1885", "followers": 400, "gravatar_id": "", "created": "2013-05-06T15:42:20Z", "name": "ASCE1885", "login": "ASCE1885", "id": "user-4355850", "type": "user", "created_at": "2013-05-06T15:42:20Z", "language": "Java", "followers_count": 400, "location": "shenzhen,China"}, {"fullname": "Dan Benjamin", "public_repo_count": 22, "score": 1.0, "repos": 22, "username": "dan", "followers": 400, "gravatar_id": "", "created": "2008-02-13T13:22:57Z", "name": "Dan Benjamin", "login": "dan", "id": "user-219", "type": "user", "created_at": "2008-02-13T13:22:57Z", "language": "Ruby", "followers_count": 400, "location": "Austin, Texas"}, {"fullname": "Ragunath Jawahar", "public_repo_count": 24, "score": 1.0, "repos": 24, "username": "ragunathjawahar", "followers": 400, "gravatar_id": "", "created": "2011-10-20T22:46:46Z", "name": "Ragunath Jawahar", "login": "ragunathjawahar", "id": "user-1141970", "type": "user", "created_at": "2011-10-20T22:46:46Z", "language": "Java", "followers_count": 400, "location": "Chennai, India"}, {"fullname": "Katharine", "public_repo_count": 28, "score": 1.0, "repos": 28, "username": "kjam", "followers": 400, "gravatar_id": "", "created": "2010-07-15T23:59:17Z", "name": "Katharine", "login": "kjam", "id": "user-333528", "type": "user", "created_at": "2010-07-15T23:59:17Z", "language": "Python", "followers_count": 400, "location": "Berlin, Germany"}, {"fullname": "Phillip Isola", "public_repo_count": 8, "score": 1.0, "repos": 8, "username": "phillipi", "followers": 400, "gravatar_id": "", "created": "2011-05-26T22:19:54Z", "name": "Phillip Isola", "login": "phillipi", "id": "user-813142", "type": "user", "created_at": "2011-05-26T22:19:54Z", "language": "C++", "followers_count": 400, "location": null}, {"fullname": "NachoSoto", "public_repo_count": 85, "score": 1.0, "repos": 85, "username": "NachoSoto", "followers": 400, "gravatar_id": "", "created": "2011-03-23T08:22:22Z", "name": "NachoSoto", "login": "NachoSoto", "id": "user-685609", "type": "user", "created_at": "2011-03-23T08:22:22Z", "language": "Swift", "followers_count": 400, "location": "San Francisco, California"}, {"fullname": "Tim Fox", "public_repo_count": 42, "score": 1.0, "repos": 42, "username": "purplefox", "followers": 400, "gravatar_id": "", "created": "2011-03-31T16:05:22Z", "name": "Tim Fox", "login": "purplefox", "id": "user-701906", "type": "user", "created_at": "2011-03-31T16:05:22Z", "language": "Java", "followers_count": 400, "location": "The moon"}, {"fullname": "\u5218\u9879", "public_repo_count": 35, "score": 1.0, "repos": 35, "username": "lexdene", "followers": 400, "gravatar_id": "", "created": "2011-03-28T02:58:19Z", "name": "\u5218\u9879", "login": "lexdene", "id": "user-694227", "type": "user", "created_at": "2011-03-28T02:58:19Z", "language": "Python", "followers_count": 400, "location": "\u4e2d\u56fd\u5317\u4eac Beijing China"}, {"fullname": "lingtao kong", "public_repo_count": 108, "score": 1.0, "repos": 108, "username": "KingNigel", "followers": 400, "gravatar_id": "", "created": "2013-01-17T02:17:09Z", "name": "lingtao kong", "login": "KingNigel", "id": "user-3291549", "type": "user", "created_at": "2013-01-17T02:17:09Z", "language": "JavaScript", "followers_count": 400, "location": "Beijing, China"}, {"fullname": "Rachael Shaw", "public_repo_count": 38, "score": 1.0, "repos": 38, "username": "rachaelshaw", "followers": 400, "gravatar_id": "", "created": "2012-12-17T19:35:13Z", "name": "Rachael Shaw", "login": "rachaelshaw", "id": "user-3065949", "type": "user", "created_at": "2012-12-17T19:35:13Z", "language": "JavaScript", "followers_count": 400, "location": "Austin, TX"}, {"fullname": "Phil Cohen", "public_repo_count": 220, "score": 1.0, "repos": 220, "username": "phlipper", "followers": 400, "gravatar_id": "", "created": "2008-02-26T19:58:08Z", "name": "Phil Cohen", "login": "phlipper", "id": "user-984", "type": "user", "created_at": "2008-02-26T19:58:08Z", "language": "Ruby", "followers_count": 400, "location": "Near Lake Tahoe, CA"}, {"fullname": "", "public_repo_count": 34, "score": 1.0, "repos": 34, "username": "yjxiong", "followers": 400, "gravatar_id": "", "created": "2014-03-02T09:57:33Z", "name": "", "login": "yjxiong", "id": "user-6830199", "type": "user", "created_at": "2014-03-02T09:57:33Z", "language": "Python", "followers_count": 400, "location": null}, {"fullname": "\u90b9\u6653\u822a", "public_repo_count": 18, "score": 1.0, "repos": 18, "username": "zouxiaohang", "followers": 400, "gravatar_id": "", "created": "2013-01-19T07:06:41Z", "name": "\u90b9\u6653\u822a", "login": "zouxiaohang", "id": "user-3312797", "type": "user", "created_at": "2013-01-19T07:06:41Z", "language": "C++", "followers_count": 400, "location": "China"}, {"fullname": "Jos\u00e9 Padilla", "public_repo_count": 195, "score": 1.0, "repos": 195, "username": "jpadilla", "followers": 400, "gravatar_id": "", "created": "2009-05-11T16:26:42Z", "name": "Jos\u00e9 Padilla", "login": "jpadilla", "id": "user-83319", "type": "user", "created_at": "2009-05-11T16:26:42Z", "language": "JavaScript", "followers_count": 400, "location": "Hartford, CT"}, {"fullname": "Ahmed Soliman Farghal", "public_repo_count": 44, "score": 1.0, "repos": 44, "username": "AhmedSoliman", "followers": 400, "gravatar_id": "", "created": "2009-03-03T11:39:50Z", "name": "Ahmed Soliman Farghal", "login": "AhmedSoliman", "id": "user-59670", "type": "user", "created_at": "2009-03-03T11:39:50Z", "language": "Scala", "followers_count": 400, "location": "London, UK"}, {"fullname": "Peter Goldsborough", "public_repo_count": 71, "score": 1.0, "repos": 71, "username": "goldsborough", "followers": 400, "gravatar_id": "", "created": "2014-01-17T13:45:30Z", "name": "Peter Goldsborough", "login": "goldsborough", "id": "user-6429851", "type": "user", "created_at": "2014-01-17T13:45:30Z", "language": "Python", "followers_count": 400, "location": "Menlo Park, CA"}, {"fullname": "Jichao Ouyang", "public_repo_count": 129, "score": 1.0, "repos": 129, "username": "jcouyang", "followers": 399, "gravatar_id": "", "created": "2011-12-02T02:18:01Z", "name": "Jichao Ouyang", "login": "jcouyang", "id": "user-1235045", "type": "user", "created_at": "2011-12-02T02:18:01Z", "language": "JavaScript", "followers_count": 399, "location": "Melbourne, AU"}, {"fullname": "Brian Advent", "public_repo_count": 54, "score": 1.0, "repos": 54, "username": "brianadvent", "followers": 399, "gravatar_id": "", "created": "2015-01-30T17:38:02Z", "name": "Brian Advent", "login": "brianadvent", "id": "user-10776593", "type": "user", "created_at": "2015-01-30T17:38:02Z", "language": "Swift", "followers_count": 399, "location": null}, {"fullname": "Andreas Gal", "public_repo_count": 65, "score": 1.0, "repos": 65, "username": "andreasgal", "followers": 399, "gravatar_id": "", "created": "2010-06-24T15:29:50Z", "name": "Andreas Gal", "login": "andreasgal", "id": "user-313748", "type": "user", "created_at": "2010-06-24T15:29:50Z", "language": "JavaScript", "followers_count": 399, "location": null}, {"fullname": "", "public_repo_count": 0, "score": 1.0, "repos": 0, "username": "googlebot", "followers": 399, "gravatar_id": "", "created": "2013-09-04T18:30:59Z", "name": "", "login": "googlebot", "id": "user-5384588", "type": "user", "created_at": "2013-09-04T18:30:59Z", "language": null, "followers_count": 399, "location": null}, {"fullname": "Zach Kelling", "public_repo_count": 237, "score": 1.0, "repos": 237, "username": "zeekay", "followers": 399, "gravatar_id": "", "created": "2010-05-24T15:26:08Z", "name": "Zach Kelling", "login": "zeekay", "id": "user-285707", "type": "user", "created_at": "2010-05-24T15:26:08Z", "language": "CoffeeScript", "followers_count": 399, "location": "curl zeekay.chat | python"}, {"fullname": "Andy Piper", "public_repo_count": 172, "score": 1.0, "repos": 172, "username": "andypiper", "followers": 399, "gravatar_id": "", "created": "2011-01-07T20:33:09Z", "name": "Andy Piper", "login": "andypiper", "id": "user-552452", "type": "user", "created_at": "2011-01-07T20:33:09Z", "language": "JavaScript", "followers_count": 399, "location": "Kingston upon Thames, UK"}, {"fullname": "Johan Tibell", "public_repo_count": 23, "score": 1.0, "repos": 23, "username": "tibbe", "followers": 399, "gravatar_id": "", "created": "2008-07-16T20:40:18Z", "name": "Johan Tibell", "login": "tibbe", "id": "user-17277", "type": "user", "created_at": "2008-07-16T20:40:18Z", "language": "Haskell", "followers_count": 399, "location": "Sydney, Australia"}, {"fullname": "Juan Lopes", "public_repo_count": 71, "score": 1.0, "repos": 71, "username": "juanplopes", "followers": 399, "gravatar_id": "", "created": "2009-04-17T17:36:42Z", "name": "Juan Lopes", "login": "juanplopes", "id": "user-74924", "type": "user", "created_at": "2009-04-17T17:36:42Z", "language": "C#", "followers_count": 399, "location": "Rio de Janeiro"}, {"fullname": "Justin Willis", "public_repo_count": 139, "score": 1.0, "repos": 139, "username": "jgw96", "followers": 399, "gravatar_id": "", "created": "2014-09-18T16:45:30Z", "name": "Justin Willis", "login": "jgw96", "id": "user-8823093", "type": "user", "created_at": "2014-09-18T16:45:30Z", "language": "JavaScript", "followers_count": 399, "location": "United States"}, {"fullname": "Masahiro Wakame", "public_repo_count": 146, "score": 1.0, "repos": 146, "username": "vvakame", "followers": 399, "gravatar_id": "", "created": "2009-09-10T12:20:08Z", "name": "Masahiro Wakame", "login": "vvakame", "id": "user-125332", "type": "user", "created_at": "2009-09-10T12:20:08Z", "language": "Java", "followers_count": 399, "location": "Tokyo, Japan"}, {"fullname": "Rob \"Hurricane\" Ashton", "public_repo_count": 156, "score": 1.0, "repos": 156, "username": "robashton", "followers": 399, "gravatar_id": "", "created": "2010-03-16T12:02:28Z", "name": "Rob \"Hurricane\" Ashton", "login": "robashton", "id": "user-223758", "type": "user", "created_at": "2010-03-16T12:02:28Z", "language": "JavaScript", "followers_count": 399, "location": "Glasgow"}, {"fullname": "Pat Allan", "public_repo_count": 164, "score": 1.0, "repos": 164, "username": "pat", "followers": 399, "gravatar_id": "", "created": "2008-04-01T01:12:11Z", "name": "Pat Allan", "login": "pat", "id": "user-4183", "type": "user", "created_at": "2008-04-01T01:12:11Z", "language": "Ruby", "followers_count": 399, "location": "Wurundjeri land / Melbourne AU"}, {"fullname": "sunerok", "public_repo_count": 67, "score": 1.0, "repos": 67, "username": "justinvforvendetta", "followers": 399, "gravatar_id": "", "created": "2014-08-14T00:50:07Z", "name": "sunerok", "login": "justinvforvendetta", "id": "user-8443713", "type": "user", "created_at": "2014-08-14T00:50:07Z", "language": "C++", "followers_count": 399, "location": "[deep.space]"}, {"fullname": "dodge", "public_repo_count": 18, "score": 1.0, "repos": 18, "username": "dodgepudding", "followers": 399, "gravatar_id": "", "created": "2011-01-05T03:06:26Z", "name": "dodge", "login": "dodgepudding", "id": "user-548031", "type": "user", "created_at": "2011-01-05T03:06:26Z", "language": "PHP", "followers_count": 399, "location": "Guangzhou"}, {"fullname": "0utKast", "public_repo_count": 89, "score": 1.0, "repos": 89, "username": "0utKast", "followers": 398, "gravatar_id": "", "created": "2011-05-25T16:11:23Z", "name": "0utKast", "login": "0utKast", "id": "user-810207", "type": "user", "created_at": "2011-05-25T16:11:23Z", "language": "JavaScript", "followers_count": 398, "location": "Playa del Ingl\u00e9s"}, {"fullname": null, "public_repo_count": 12, "score": 1.0, "repos": 12, "username": "monkeyWie", "followers": 398, "gravatar_id": "", "created": "2015-07-03T03:42:47Z", "name": null, "login": "monkeyWie", "id": "user-13160176", "type": "user", "created_at": "2015-07-03T03:42:47Z", "language": "Java", "followers_count": 398, "location": null}, {"fullname": "Peggy Rayzis", "public_repo_count": 50, "score": 1.0, "repos": 50, "username": "peggyrayzis", "followers": 398, "gravatar_id": "", "created": "2016-03-22T22:22:20Z", "name": "Peggy Rayzis", "login": "peggyrayzis", "id": "user-18017067", "type": "user", "created_at": "2016-03-22T22:22:20Z", "language": "JavaScript", "followers_count": 398, "location": "New York, NY"}, {"fullname": "Stefan Hedman", "public_repo_count": 51, "score": 1.0, "repos": 51, "username": "schteppe", "followers": 398, "gravatar_id": "", "created": "2011-09-19T20:05:50Z", "name": "Stefan Hedman", "login": "schteppe", "id": "user-1063152", "type": "user", "created_at": "2011-09-19T20:05:50Z", "language": "JavaScript", "followers_count": 398, "location": "Stockholm, Sweden"}, {"fullname": "Jacky Tsang", "public_repo_count": 58, "score": 1.0, "repos": 58, "username": "zrong", "followers": 398, "gravatar_id": "", "created": "2010-06-09T00:53:17Z", "name": "Jacky Tsang", "login": "zrong", "id": "user-300413", "type": "user", "created_at": "2010-06-09T00:53:17Z", "language": "ActionScript", "followers_count": 398, "location": "WUHAN"}, {"fullname": "", "public_repo_count": 6, "score": 1.0, "repos": 6, "username": "ephtracy", "followers": 398, "gravatar_id": "", "created": "2013-09-12T18:27:36Z", "name": "", "login": "ephtracy", "id": "user-5446525", "type": "user", "created_at": "2013-09-12T18:27:36Z", "language": "HTML", "followers_count": 398, "location": null}, {"fullname": "iThinker_YZ", "public_repo_count": 15, "score": 1.0, "repos": 15, "username": "iThinkerYZ", "followers": 398, "gravatar_id": "", "created": "2013-09-22T07:34:40Z", "name": "iThinker_YZ", "login": "iThinkerYZ", "id": "user-5511525", "type": "user", "created_at": "2013-09-22T07:34:40Z", "language": "Objective-C", "followers_count": 398, "location": null}, {"fullname": "Zhixuan Lai", "public_repo_count": 45, "score": 1.0, "repos": 45, "username": "zhxnlai", "followers": 398, "gravatar_id": "", "created": "2013-06-14T04:57:53Z", "name": "Zhixuan Lai", "login": "zhxnlai", "id": "user-4694896", "type": "user", "created_at": "2013-06-14T04:57:53Z", "language": "Swift", "followers_count": 398, "location": "Los Angeles, CA"}, {"fullname": "Takuya Fujiwara", "public_repo_count": 167, "score": 1.0, "repos": 167, "username": "tyru", "followers": 398, "gravatar_id": "", "created": "2009-01-21T06:15:37Z", "name": "Takuya Fujiwara", "login": "tyru", "id": "user-48169", "type": "user", "created_at": "2009-01-21T06:15:37Z", "language": "Vim script", "followers_count": 398, "location": "Tokyo, Japan"}, {"fullname": "", "public_repo_count": 10, "score": 1.0, "repos": 10, "username": "drduh", "followers": 398, "gravatar_id": "", "created": "2015-05-16T16:50:32Z", "name": "", "login": "drduh", "id": "user-12475110", "type": "user", "created_at": "2015-05-16T16:50:32Z", "language": "Shell", "followers_count": 398, "location": null}, {"fullname": "Karan Desai", "public_repo_count": 19, "score": 1.0, "repos": 19, "username": "kdexd", "followers": 398, "gravatar_id": "", "created": "2015-01-12T06:03:25Z", "name": "Karan Desai", "login": "kdexd", "id": "user-10494087", "type": "user", "created_at": "2015-01-12T06:03:25Z", "language": "Python", "followers_count": 398, "location": "IIT Roorkee"}, {"fullname": "Andres Suarez", "public_repo_count": 86, "score": 1.0, "repos": 86, "username": "zertosh", "followers": 398, "gravatar_id": "", "created": "2011-06-05T15:24:11Z", "name": "Andres Suarez", "login": "zertosh", "id": "user-830952", "type": "user", "created_at": "2011-06-05T15:24:11Z", "language": "JavaScript", "followers_count": 398, "location": "New York, NY"}, {"fullname": "Deepak Pathak", "public_repo_count": 11, "score": 1.0, "repos": 11, "username": "pathak22", "followers": 398, "gravatar_id": "", "created": "2014-10-05T23:08:44Z", "name": "Deepak Pathak", "login": "pathak22", "id": "user-9029761", "type": "user", "created_at": "2014-10-05T23:08:44Z", "language": "C++", "followers_count": 398, "location": "Berkelely, CA"}, {"fullname": "Eiji Kitamura", "public_repo_count": 63, "score": 1.0, "repos": 63, "username": "agektmr", "followers": 398, "gravatar_id": "", "created": "2010-03-08T06:11:10Z", "name": "Eiji Kitamura", "login": "agektmr", "id": "user-218144", "type": "user", "created_at": "2010-03-08T06:11:10Z", "language": "JavaScript", "followers_count": 398, "location": "Tokyo, Japan"}, {"fullname": "ftiasch", "public_repo_count": 11, "score": 1.0, "repos": 11, "username": "ftiasch", "followers": 397, "gravatar_id": "", "created": "2011-03-16T06:09:07Z", "name": "ftiasch", "login": "ftiasch", "id": "user-672477", "type": "user", "created_at": "2011-03-16T06:09:07Z", "language": "C++", "followers_count": 397, "location": "Shanghai, China"}, {"fullname": "Robert Payne", "public_repo_count": 20, "score": 1.0, "repos": 20, "username": "robertjpayne", "followers": 397, "gravatar_id": "", "created": "2010-03-02T23:28:25Z", "name": "Robert Payne", "login": "robertjpayne", "id": "user-214288", "type": "user", "created_at": "2010-03-02T23:28:25Z", "language": "Swift", "followers_count": 397, "location": "Auckland, New Zealand"}, {"fullname": "Mahmoud Zalt", "public_repo_count": 10, "score": 1.0, "repos": 10, "username": "Mahmoudz", "followers": 397, "gravatar_id": "", "created": "2012-07-16T12:08:18Z", "name": "Mahmoud Zalt", "login": "Mahmoudz", "id": "user-1983984", "type": "user", "created_at": "2012-07-16T12:08:18Z", "language": "PHP", "followers_count": 397, "location": "Amsterdam, Netherlands"}, {"fullname": "Denis Pushkarev", "public_repo_count": 3, "score": 1.0, "repos": 3, "username": "zloirock", "followers": 397, "gravatar_id": "", "created": "2012-08-24T19:57:37Z", "name": "Denis Pushkarev", "login": "zloirock", "id": "user-2213682", "type": "user", "created_at": "2012-08-24T19:57:37Z", "language": "JavaScript", "followers_count": 397, "location": "Russia, Barnaul"}, {"fullname": "Jonas Jongejan", "public_repo_count": 99, "score": 1.0, "repos": 99, "username": "HalfdanJ", "followers": 397, "gravatar_id": "", "created": "2010-03-21T22:18:13Z", "name": "Jonas Jongejan", "login": "HalfdanJ", "id": "user-227529", "type": "user", "created_at": "2010-03-21T22:18:13Z", "language": "C++", "followers_count": 397, "location": "New York"}, {"fullname": "Eric Huang", "public_repo_count": 43, "score": 1.0, "repos": 43, "username": "ele828", "followers": 397, "gravatar_id": "", "created": "2014-08-24T02:51:48Z", "name": "Eric Huang", "login": "ele828", "id": "user-8534639", "type": "user", "created_at": "2014-08-24T02:51:48Z", "language": "JavaScript", "followers_count": 397, "location": "Xiamen, China"}, {"fullname": "Jim Vallandingham", "public_repo_count": 247, "score": 1.0, "repos": 247, "username": "vlandham", "followers": 397, "gravatar_id": "", "created": "2008-05-05T17:34:45Z", "name": "Jim Vallandingham", "login": "vlandham", "id": "user-9369", "type": "user", "created_at": "2008-05-05T17:34:45Z", "language": "JavaScript", "followers_count": 397, "location": "Seattle, WA"}, {"fullname": "Alexandru Nedelcu", "public_repo_count": 51, "score": 1.0, "repos": 51, "username": "alexandru", "followers": 397, "gravatar_id": "", "created": "2008-05-28T11:36:21Z", "name": "Alexandru Nedelcu", "login": "alexandru", "id": "user-11753", "type": "user", "created_at": "2008-05-28T11:36:21Z", "language": "Scala", "followers_count": 397, "location": "Rom\u00e2nia"}, {"fullname": "Manraj Singh", "public_repo_count": 198, "score": 1.0, "repos": 198, "username": "ManrajGrover", "followers": 396, "gravatar_id": "", "created": "2013-10-12T20:26:02Z", "name": "Manraj Singh", "login": "ManrajGrover", "id": "user-5673050", "type": "user", "created_at": "2013-10-12T20:26:02Z", "language": "JavaScript", "followers_count": 396, "location": "Bangalore, India"}, {"fullname": "Umed Khudoiberdiev", "public_repo_count": 51, "score": 1.0, "repos": 51, "username": "pleerock", "followers": 396, "gravatar_id": "", "created": "2012-05-18T19:40:52Z", "name": "Umed Khudoiberdiev", "login": "pleerock", "id": "user-1753397", "type": "user", "created_at": "2012-05-18T19:40:52Z", "language": "TypeScript", "followers_count": 396, "location": "Anywhere"}, {"fullname": "Smitha Milli", "public_repo_count": 55, "score": 1.0, "repos": 55, "username": "smilli", "followers": 396, "gravatar_id": "", "created": "2013-07-29T00:41:21Z", "name": "Smitha Milli", "login": "smilli", "id": "user-5109188", "type": "user", "created_at": "2013-07-29T00:41:21Z", "language": "Python", "followers_count": 396, "location": "Berkeley,CA"}, {"fullname": "Joshua Timberman", "public_repo_count": 375, "score": 1.0, "repos": 375, "username": "jtimberman", "followers": 396, "gravatar_id": "", "created": "2008-06-03T21:11:35Z", "name": "Joshua Timberman", "login": "jtimberman", "id": "user-12483", "type": "user", "created_at": "2008-06-03T21:11:35Z", "language": "Ruby", "followers_count": 396, "location": "Colorado"}, {"fullname": "Shyam Seshadri", "public_repo_count": 19, "score": 1.0, "repos": 19, "username": "shyamseshadri", "followers": 396, "gravatar_id": "", "created": "2010-03-24T17:37:06Z", "name": "Shyam Seshadri", "login": "shyamseshadri", "id": "user-229613", "type": "user", "created_at": "2010-03-24T17:37:06Z", "language": "JavaScript", "followers_count": 396, "location": "Navi Mumbai, India"}, {"fullname": "Paul Tagliamonte", "public_repo_count": 330, "score": 1.0, "repos": 330, "username": "paultag", "followers": 396, "gravatar_id": "", "created": "2009-09-28T22:47:50Z", "name": "Paul Tagliamonte", "login": "paultag", "id": "user-132447", "type": "user", "created_at": "2009-09-28T22:47:50Z", "language": "Python", "followers_count": 396, "location": "X5O!P%@AP[4\\PZX54(P^)7CC)7}$EICAR-STANDARD-ANTIVIRUS-TEST-FILE!$H+H*"}, {"fullname": "\u82cf\u5251\u6797", "public_repo_count": 18, "score": 1.0, "repos": 18, "username": "bojone", "followers": 396, "gravatar_id": "", "created": "2014-10-12T03:02:59Z", "name": "\u82cf\u5251\u6797", "login": "bojone", "id": "user-9159613", "type": "user", "created_at": "2014-10-12T03:02:59Z", "language": "Python", "followers_count": 396, "location": null}, {"fullname": "M.Yasoob Ullah Khalid \u263a", "public_repo_count": 165, "score": 1.0, "repos": 165, "username": "yasoob", "followers": 396, "gravatar_id": "", "created": "2013-02-25T17:55:16Z", "name": "M.Yasoob Ullah Khalid \u263a", "login": "yasoob", "id": "user-3696393", "type": "user", "created_at": "2013-02-25T17:55:16Z", "language": "Python", "followers_count": 396, "location": "Pakistan"}, {"fullname": "\u674e\u590f\u9a70", "public_repo_count": 17, "score": 1.0, "repos": 17, "username": "oldmanpushcart", "followers": 395, "gravatar_id": "", "created": "2012-11-17T01:41:27Z", "name": "\u674e\u590f\u9a70", "login": "oldmanpushcart", "id": "user-2818301", "type": "user", "created_at": "2012-11-17T01:41:27Z", "language": "Java", "followers_count": 395, "location": "\u4e2d\u56fd\u6d59\u6c5f\u7701\u676d\u5dde\u5e02"}, {"fullname": "Yuki Nishijima", "public_repo_count": 61, "score": 1.0, "repos": 61, "username": "yuki24", "followers": 395, "gravatar_id": "", "created": "2010-09-03T08:42:03Z", "name": "Yuki Nishijima", "login": "yuki24", "id": "user-386234", "type": "user", "created_at": "2010-09-03T08:42:03Z", "language": "Ruby", "followers_count": 395, "location": "New York, NY"}, {"fullname": "Denis Stoyanov", "public_repo_count": 718, "score": 1.0, "repos": 718, "username": "xgrommx", "followers": 395, "gravatar_id": "", "created": "2012-03-04T14:30:17Z", "name": "Denis Stoyanov", "login": "xgrommx", "id": "user-1499594", "type": "user", "created_at": "2012-03-04T14:30:17Z", "language": "JavaScript", "followers_count": 395, "location": "UA"}, {"fullname": "othree", "public_repo_count": 181, "score": 1.0, "repos": 181, "username": "othree", "followers": 395, "gravatar_id": "", "created": "2008-07-09T04:21:39Z", "name": "othree", "login": "othree", "id": "user-16474", "type": "user", "created_at": "2008-07-09T04:21:39Z", "language": "JavaScript", "followers_count": 395, "location": "Taipei, Taiwan"}, {"fullname": "Turtuvshin Byambaa", "public_repo_count": 22, "score": 1.0, "repos": 22, "username": "tortuvshin", "followers": 395, "gravatar_id": "", "created": "2015-06-03T22:59:33Z", "name": "Turtuvshin Byambaa", "login": "tortuvshin", "id": "user-12738721", "type": "user", "created_at": "2015-06-03T22:59:33Z", "language": "Java", "followers_count": 395, "location": "Ulaanbaatar, Mongolia"}, {"fullname": "\u5434\u665f Wu Sheng", "public_repo_count": 79, "score": 1.0, "repos": 79, "username": "wu-sheng", "followers": 395, "gravatar_id": "", "created": "2013-09-12T07:04:16Z", "name": "\u5434\u665f Wu Sheng", "login": "wu-sheng", "id": "user-5441976", "type": "user", "created_at": "2013-09-12T07:04:16Z", "language": "Java", "followers_count": 395, "location": "Beijing, China"}, {"fullname": "Aniruddha Adhikary", "public_repo_count": 35, "score": 1.0, "repos": 35, "username": "aniruddha-adhikary", "followers": 395, "gravatar_id": "", "created": "2011-07-22T17:44:41Z", "name": "Aniruddha Adhikary", "login": "aniruddha-adhikary", "id": "user-932949", "type": "user", "created_at": "2011-07-22T17:44:41Z", "language": "Python", "followers_count": 395, "location": "Dhaka, Bangladesh"}, {"fullname": "Honza Kr\u00e1l", "public_repo_count": 28, "score": 1.0, "repos": 28, "username": "HonzaKral", "followers": 395, "gravatar_id": "", "created": "2008-11-01T13:02:27Z", "name": "Honza Kr\u00e1l", "login": "HonzaKral", "id": "user-32132", "type": "user", "created_at": "2008-11-01T13:02:27Z", "language": "Python", "followers_count": 395, "location": "Czech Republic"}, {"fullname": "Michael Villar", "public_repo_count": 33, "score": 1.0, "repos": 33, "username": "michaelvillar", "followers": 395, "gravatar_id": "", "created": "2009-12-29T00:13:05Z", "name": "Michael Villar", "login": "michaelvillar", "id": "user-173322", "type": "user", "created_at": "2009-12-29T00:13:05Z", "language": "JavaScript", "followers_count": 395, "location": "San Francisco"}, {"fullname": "Petar Maymounkov", "public_repo_count": 30, "score": 1.0, "repos": 30, "username": "petar", "followers": 395, "gravatar_id": "", "created": "2010-05-24T01:15:34Z", "name": "Petar Maymounkov", "login": "petar", "id": "user-285131", "type": "user", "created_at": "2010-05-24T01:15:34Z", "language": "Go", "followers_count": 395, "location": "Brooklyn, NY"}, {"fullname": "Daniel Sperl", "public_repo_count": 11, "score": 1.0, "repos": 11, "username": "PrimaryFeather", "followers": 395, "gravatar_id": "", "created": "2011-01-04T18:01:57Z", "name": "Daniel Sperl", "login": "PrimaryFeather", "id": "user-547347", "type": "user", "created_at": "2011-01-04T18:01:57Z", "language": "Ruby", "followers_count": 395, "location": "Austria"}, {"fullname": "Nikolay Bachiyski", "public_repo_count": 55, "score": 1.0, "repos": 55, "username": "nb", "followers": 394, "gravatar_id": "", "created": "2008-10-07T16:14:32Z", "name": "Nikolay Bachiyski", "login": "nb", "id": "user-27954", "type": "user", "created_at": "2008-10-07T16:14:32Z", "language": "JavaScript", "followers_count": 394, "location": "Sofia, Bulgaria"}, {"fullname": "Wang Shidong", "public_repo_count": 210, "score": 1.0, "repos": 210, "username": "wsdjeg", "followers": 394, "gravatar_id": "", "created": "2015-07-01T23:21:16Z", "name": "Wang Shidong", "login": "wsdjeg", "id": "user-13142418", "type": "user", "created_at": "2015-07-01T23:21:16Z", "language": "Vim script", "followers_count": 394, "location": "China"}, {"fullname": "Christian Roman", "public_repo_count": 34, "score": 1.0, "repos": 34, "username": "chroman", "followers": 394, "gravatar_id": "", "created": "2010-10-30T19:05:32Z", "name": "Christian Roman", "login": "chroman", "id": "user-461021", "type": "user", "created_at": "2010-10-30T19:05:32Z", "language": "Objective-C", "followers_count": 394, "location": "Mexico"}, {"fullname": "erik", "public_repo_count": 13, "score": 1.0, "repos": 13, "username": "erik168", "followers": 394, "gravatar_id": "", "created": "2011-03-29T03:36:29Z", "name": "erik", "login": "erik168", "id": "user-696441", "type": "user", "created_at": "2011-03-29T03:36:29Z", "language": "JavaScript", "followers_count": 394, "location": "Beijing"}]}